spann/__init__.py
spann/functions.py
spann/model.py
spann/preprocess.py
spann-0.0.5.dist-info/LICENSE
spann-0.0.5.dist-info/METADATA
spann-0.0.5.dist-info/WHEEL
spann-0.0.5.dist-info/entry_points.txt
spann-0.0.5.dist-info/RECORD
