Metadata-Version: 2.1
Name: spann
Version: 0.0.5
Summary: 
Home-page: https://github.com/ddb-qiwang/SPANN-torch
License: Apache-2.0
Author: ddb-qiwang
Requires-Python: >=3.7.1,<4.0.0
Classifier: License :: OSI Approved :: Apache Software License
Classifier: Programming Language :: Python :: 3
Classifier: Programming Language :: Python :: 3.8
Classifier: Programming Language :: Python :: 3.9
Classifier: Programming Language :: Python :: 3.10
Classifier: Programming Language :: Python :: 3.11
Classifier: Programming Language :: Python :: 3.12
Requires-Dist: easydl (>=2.0,<2.1)
Requires-Dist: matplotlib (>=3.5.3,<3.6.0)
Requires-Dist: numpy (>=1.21,<1.22)
Requires-Dist: pandas (>=1.3.5,<1.4.0)
Requires-Dist: pot (>=0.8.2,<0.9.0)
Requires-Dist: scanpy (>=1.9,<1.10)
Requires-Dist: scikit-learn (==0.24)
Requires-Dist: scipy (>=1.6,<1.7)
Requires-Dist: seaborn (>=0.9,<0.10)
Requires-Dist: torch (>=1.10,<1.11)
Requires-Dist: typing-extensions (>=4.0.0,<4.1.0)
Project-URL: Repository, https://github.com/ddb-qiwang/SPANN-torch
